<?xml version="1.0" encoding="utf-8" ?>
<dwsync>
<file name="2002.htm" local="128384001000000000" remote="128384001000000000" testing="0" />
<file name="adver.htm" local="128480916932331956" remote="128481559200000000" testing="0" />
<file name="attic.htm" local="127920384000000000" remote="128545737600000000" testing="0" />
<file name="beach.htm" local="128384001000000000" remote="128384001000000000" testing="0" />
<file name="biz.htm" local="128384001000000000" remote="128384001000000000" testing="0" />
<file name="BulbBox.htm" local="128384000400000000" remote="128384000400000000" testing="0" />
<file name="bush.htm" local="128384000400000000" remote="128384000400000000" testing="0" />
<file name="castle.htm" local="128384000400000000" remote="128384000400000000" testing="0" />
<file name="child.htm" local="128384000400000000" remote="128384000400000000" testing="0" />
<file name="classic.htm" local="128480916869721956" remote="128481559200000000" testing="0" />
<file name="coday.htm" local="128384000400000000" remote="128384000400000000" testing="0" />
<file name="colour.htm" local="128384000400000000" remote="128384000400000000" testing="0" />
<file name="corpo.htm" local="128384000400000000" remote="128384000400000000" testing="0" />
<file name="cow.htm" local="128384000400000000" remote="128384000400000000" testing="0" />
<file name="cyber.htm" local="128480770344391956" remote="128481559200000000" testing="0" />
<file name="djam.htm" local="128384000400000000" remote="128384000400000000" testing="0" />
<file name="era.htm" local="128384000400000000" remote="128384000400000000" testing="0" />
<file name="era2.htm" local="128384000400000000" remote="128384000400000000" testing="0" />
<file name="festival.htm" local="128384000400000000" remote="128384000400000000" testing="0" />
<file name="food.htm" local="128384000400000000" remote="128384000400000000" testing="0" />
<file name="food2.htm" local="128384000400000000" remote="128384000400000000" testing="0" />
<file name="fooda.htm" local="128384000400000000" remote="128384000400000000" testing="0" />
<file name="foodc.htm" local="128384000400000000" remote="128384000400000000" testing="0" />
<file name="foodi.htm" local="128384000400000000" remote="128384000400000000" testing="0" />
<file name="foodj.htm" local="128384000400000000" remote="128384000400000000" testing="0" />
<file name="foodm.htm" local="128384000400000000" remote="128384000400000000" testing="0" />
<file name="foodsp.htm" local="128384000400000000" remote="128384000400000000" testing="0" />
<file name="fpics.htm" local="128384000400000000" remote="128384000400000000" testing="0" />
<file name="fstreet.htm" local="128384000400000000" remote="128384000400000000" testing="0" />
<file name="geneology.htm" local="128384000400000000" remote="128384000400000000" testing="0" />
<file name="green.htm" local="128384000400000000" remote="128384000400000000" testing="0" />
<file name="green1.htm" local="128384000400000000" remote="128384000400000000" testing="0" />
<file name="green2.htm" local="128384000400000000" remote="128384000400000000" testing="0" />
<file name="green3.htm" local="128384000400000000" remote="128384000400000000" testing="0" />
<file name="hannah.htm" local="128384000400000000" remote="128384000400000000" testing="0" />
<file name="hawks.htm" local="128384000400000000" remote="128384000400000000" testing="0" />
<file name="henrick.htm" local="128384000400000000" remote="128384000400000000" testing="0" />
<file name="horoscopes.htm" local="128384000400000000" remote="128384000400000000" testing="0" />
<file name="house.htm" local="128384000400000000" remote="128384000400000000" testing="0" />
<file name="housefin.htm" local="128384000400000000" remote="128384000400000000" testing="0" />
<file name="illus.htm" local="128481556451760000" remote="128481559200000000" testing="0" />
<file name="index.htm" local="128542749600000000" remote="128542749600000000" testing="0" />
<file name="ire.htm" local="128384000400000000" remote="128384000400000000" testing="0" />
<file name="links.htm" local="128542785259967789" remote="128542749600000000" testing="0" />
<file name="magaz.htm" local="128481511697000000" remote="128481559200000000" testing="0" />
<file name="magfeathered.htm" local="128384000400000000" remote="128384000400000000" testing="0" />
<file name="maglights.htm" local="128384000400000000" remote="128384000400000000" testing="0" />
<file name="magmusic.htm" local="128384000400000000" remote="128384000400000000" testing="0" />
<file name="magsrilanka.htm" local="128384000400000000" remote="128384000400000000" testing="0" />
<file name="meanie.htm" local="128384000400000000" remote="128384000400000000" testing="0" />
<file name="menu.htm" local="128384000400000000" remote="128384000400000000" testing="0" />
<file name="menui.htm" local="128384000400000000" remote="128384000400000000" testing="0" />
<file name="million.htm" local="128384000400000000" remote="128384000400000000" testing="0" />
<file name="montage.htm" local="128384000400000000" remote="128384000400000000" testing="0" />
<file name="news.htm" local="128384000400000000" remote="128384000400000000" testing="0" />
<file name="octo.htm" local="128384000400000000" remote="128384000400000000" testing="0" />
<file name="olym.htm" local="128384000400000000" remote="128384000400000000" testing="0" />
<file name="olym1.htm" local="128384000400000000" remote="128384000400000000" testing="0" />
<file name="olym2.htm" local="128384000400000000" remote="128384000400000000" testing="0" />
<file name="olym3.htm" local="128384000400000000" remote="128384000400000000" testing="0" />
<file name="olym4.htm" local="128384000400000000" remote="128384000400000000" testing="0" />
<file name="paint.htm" local="128384000400000000" remote="128384000400000000" testing="0" />
<file name="painting.htm" local="128384000400000000" remote="128384000400000000" testing="0" />
<file name="photog.htm" local="128384000400000000" remote="128384000400000000" testing="0" />
<file name="platform.htm" local="128384000400000000" remote="128384000400000000" testing="0" />
<file name="princesst.htm" local="128384000400000000" remote="128384000400000000" testing="0" />
<file name="race.htm" local="128384000400000000" remote="128384000400000000" testing="0" />
<file name="recru2.htm" local="128384000400000000" remote="128384000400000000" testing="0" />
<file name="recrut.htm" local="128384000400000000" remote="128384000400000000" testing="0" />
<file name="redboat.htm" local="128384000400000000" remote="128384000400000000" testing="0" />
<file name="reJurassic.htm" local="128384000400000000" remote="128384000400000000" testing="0" />
<file name="review.htm" local="128384000400000000" remote="128384000400000000" testing="0" />
<file name="ruud.htm" local="128384000400000000" remote="128384000400000000" testing="0" />
<file name="salt.htm" local="128384000400000000" remote="128384000400000000" testing="0" />
<file name="shelt.htm" local="128480770121251956" remote="128481559200000000" testing="0" />
<file name="shop.htm" local="128384000400000000" remote="128384000400000000" testing="0" />
<file name="sixboats.htm" local="128384000400000000" remote="128384000400000000" testing="0" />
<file name="snow.htm" local="128384000400000000" remote="128384000400000000" testing="0" />
<file name="speed.htm" local="128384000400000000" remote="128384000400000000" testing="0" />
<file name="stadium.htm" local="128384000400000000" remote="128384000400000000" testing="0" />
<file name="sunset.htm" local="128384000400000000" remote="128384000400000000" testing="0" />
<file name="suspect.htm" local="128384000400000000" remote="128384000400000000" testing="0" />
<file name="texture.htm" local="128384000400000000" remote="128384000400000000" testing="0" />
<file name="TMP1139431643.htm" local="128384000400000000" remote="128384000400000000" testing="0" />
<file name="travelers.htm" local="128384000400000000" remote="128384000400000000" testing="0" />
<file name="trees.htm" local="128384000400000000" remote="128384000400000000" testing="0" />
<file name="uswork.htm" local="128384000400000000" remote="128384000400000000" testing="0" />
<file name="virtualworld.htm" local="128384000400000000" remote="128384000400000000" testing="0" />
<file name="webde.htm" local="128384000400000000" remote="128384000400000000" testing="0" />
<file name="wedd.htm" local="128480916693381956" remote="128481559200000000" testing="0" />
<file name="magfortiescover.html" local="128483510382785818" remote="128483511000000000" testing="0" />
<file name="magforties.html" local="128483510382295818" remote="128483511000000000" testing="0" />
<file name="magbanana.html" local="128483510382575818" remote="128483511000000000" testing="0" />
<file name="magint2.html" local="128481511592730000" remote="128481559200000000" testing="0" />
<file name="magtrip.html" local="128481510339560000" remote="128481559200000000" testing="0" />
<file name="magwinch.html" local="128481509611730000" remote="128481559200000000" testing="0" />
<file name="magglobal.html" local="128481507999530000" remote="128481559200000000" testing="0" />
<file name="magcircus.html" local="128481506699480000" remote="128481559200000000" testing="0" />
<file name="magboxer.html" local="128481505705430000" remote="128481559200000000" testing="0" />
<file name="magwinchburgh.html" local="128480800128101956" remote="128481559200000000" testing="0" />
<file name="magint1.html" local="128480789695731956" remote="128481559200000000" testing="0" />
<file name="snowmovie.html" local="128525488211650201" remote="128525455200000000" testing="0" />
<file name="3. Work This Out.mp3" local="128563080437116004" remote="128563066800000000" testing="0" />
</dwsync>